[
    {
        "model": "myblogapp.Skill",
        "pk": 1,
        "fields": {
            "type": "css",
            "title": "以下内容仅做测试使用，文章内容不具有任何意义",
            "abstract": "很多网站登录时都采用了极验验证码作为区分正常用户和爬虫程序的方法之一，\n                    B站正是其中的一个，只要掌握了破解的思路和方法，即使是面对不一样的网站也可以采用相似的方法进行破解。\n                    本文主要从破解思路来向大家分享破解的过程，最后后放上源码供大家参考和指正！\n                    本文主要从破解思路来向大家分享破解的过程，最后后放上源码供大家参考和指正！",
            "href": "/skill/css001.html",
            "time": "2019-07-26 14:50"
        }
    },
    {
        "model": "myblogapp.Skill",
        "pk": 2,
        "fields": {
            "type": "css",
            "title": "以下内容仅做测试使用，文章内容不具有任何意义",
            "abstract": "很多网站登录时都采用了极验验证码作为区分正常用户和爬虫程序的方法之一，\n                    B站正是其中的一个，只要掌握了破解的思路和方法，即使是面对不一样的网站也可以采用相似的方法进行破解。\n                    本文主要从破解思路来向大家分享破解的过程，最后后放上源码供大家参考和指正！\n                    本文主要从破解思路来向大家分享破解的过程，最后后放上源码供大家参考和指正！",
            "href": "/skill/css002.html",
            "time": "2019-07-26 14:50"
        }
    },
    {
        "model": "myblogapp.Skill",
        "pk": 3,
        "fields": {
            "type": "django",
            "title": "以下内容仅做测试使用，文章内容不具有任何意义",
            "abstract": "很多网站登录时都采用了极验验证码作为区分正常用户和爬虫程序的方法之一，\n                    B站正是其中的一个，只要掌握了破解的思路和方法，即使是面对不一样的网站也可以采用相似的方法进行破解。\n                    本文主要从破解思路来向大家分享破解的过程，最后后放上源码供大家参考和指正！\n                    本文主要从破解思路来向大家分享破解的过程，最后后放上源码供大家参考和指正！",
            "href": "/skill/django001.html",
            "time": "2019-07-26 14:50"
        }
    },
    {
        "model": "myblogapp.Skill",
        "pk": 4,
        "fields": {
            "type": "html",
            "title": "以下内容仅做测试使用，文章内容不具有任何意义",
            "abstract": "很多网站登录时都采用了极验验证码作为区分正常用户和爬虫程序的方法之一，\n                    B站正是其中的一个，只要掌握了破解的思路和方法，即使是面对不一样的网站也可以采用相似的方法进行破解。\n                    本文主要从破解思路来向大家分享破解的过程，最后后放上源码供大家参考和指正！\n                    本文主要从破解思路来向大家分享破解的过程，最后后放上源码供大家参考和指正！",
            "href": "/skill/html001.html",
            "time": "2019-07-26 14:50"
        }
    },
    {
        "model": "myblogapp.Skill",
        "pk": 5,
        "fields": {
            "type": "html",
            "title": "以下内容仅做测试使用，文章内容不具有任何意义",
            "abstract": "很多网站登录时都采用了极验验证码作为区分正常用户和爬虫程序的方法之一，\n                    B站正是其中的一个，只要掌握了破解的思路和方法，即使是面对不一样的网站也可以采用相似的方法进行破解。\n                    本文主要从破解思路来向大家分享破解的过程，最后后放上源码供大家参考和指正！\n                    本文主要从破解思路来向大家分享破解的过程，最后后放上源码供大家参考和指正！",
            "href": "/skill/html002.html",
            "time": "2019-07-26 14:50"
        }
    },
    {
        "model": "myblogapp.Skill",
        "pk": 6,
        "fields": {
            "type": "html",
            "title": "以下内容仅做测试使用，文章内容不具有任何意义",
            "abstract": "很多网站登录时都采用了极验验证码作为区分正常用户和爬虫程序的方法之一，\n                    B站正是其中的一个，只要掌握了破解的思路和方法，即使是面对不一样的网站也可以采用相似的方法进行破解。\n                    本文主要从破解思路来向大家分享破解的过程，最后后放上源码供大家参考和指正！\n                    本文主要从破解思路来向大家分享破解的过程，最后后放上源码供大家参考和指正！",
            "href": "/skill/html003.html",
            "time": "2019-07-26 14:50"
        }
    },
    {
        "model": "myblogapp.Skill",
        "pk": 7,
        "fields": {
            "type": "javascript",
            "title": "以下内容仅做测试使用，文章内容不具有任何意义",
            "abstract": "很多网站登录时都采用了极验验证码作为区分正常用户和爬虫程序的方法之一，\n                    B站正是其中的一个，只要掌握了破解的思路和方法，即使是面对不一样的网站也可以采用相似的方法进行破解。\n                    本文主要从破解思路来向大家分享破解的过程，最后后放上源码供大家参考和指正！\n                    本文主要从破解思路来向大家分享破解的过程，最后后放上源码供大家参考和指正！",
            "href": "/skill/js001.html",
            "time": "2019-07-26 14:50"
        }
    },
    {
        "model": "myblogapp.Skill",
        "pk": 8,
        "fields": {
            "type": "javascript",
            "title": "以下内容仅做测试使用，文章内容不具有任何意义",
            "abstract": "很多网站登录时都采用了极验验证码作为区分正常用户和爬虫程序的方法之一，\n                    B站正是其中的一个，只要掌握了破解的思路和方法，即使是面对不一样的网站也可以采用相似的方法进行破解。\n                    本文主要从破解思路来向大家分享破解的过程，最后后放上源码供大家参考和指正！\n                    本文主要从破解思路来向大家分享破解的过程，最后后放上源码供大家参考和指正！",
            "href": "/skill/js002.html",
            "time": "2019-07-26 14:50"
        }
    },
    {
        "model": "myblogapp.Skill",
        "pk": 9,
        "fields": {
            "type": "javascript",
            "title": "以下内容仅做测试使用，文章内容不具有任何意义",
            "abstract": "很多网站登录时都采用了极验验证码作为区分正常用户和爬虫程序的方法之一，\n                    B站正是其中的一个，只要掌握了破解的思路和方法，即使是面对不一样的网站也可以采用相似的方法进行破解。\n                    本文主要从破解思路来向大家分享破解的过程，最后后放上源码供大家参考和指正！\n                    本文主要从破解思路来向大家分享破解的过程，最后后放上源码供大家参考和指正！",
            "href": "/skill/js003.html",
            "time": "2019-07-26 14:50"
        }
    },
    {
        "model": "myblogapp.Skill",
        "pk": 10,
        "fields": {
            "type": "javascript",
            "title": "以下内容仅做测试使用，文章内容不具有任何意义",
            "abstract": "很多网站登录时都采用了极验验证码作为区分正常用户和爬虫程序的方法之一，\n                    B站正是其中的一个，只要掌握了破解的思路和方法，即使是面对不一样的网站也可以采用相似的方法进行破解。\n                    本文主要从破解思路来向大家分享破解的过程，最后后放上源码供大家参考和指正！\n                    本文主要从破解思路来向大家分享破解的过程，最后后放上源码供大家参考和指正！",
            "href": "/skill/js004.html",
            "time": "2019-07-26 14:50"
        }
    },
    {
        "model": "myblogapp.Skill",
        "pk": 11,
        "fields": {
            "type": "javascript",
            "title": "以下内容仅做测试使用，文章内容不具有任何意义",
            "abstract": "很多网站登录时都采用了极验验证码作为区分正常用户和爬虫程序的方法之一，\n                    B站正是其中的一个，只要掌握了破解的思路和方法，即使是面对不一样的网站也可以采用相似的方法进行破解。\n                    本文主要从破解思路来向大家分享破解的过程，最后后放上源码供大家参考和指正！\n                    本文主要从破解思路来向大家分享破解的过程，最后后放上源码供大家参考和指正！",
            "href": "/skill/js005.html",
            "time": "2019-07-26 14:50"
        }
    },
    {
        "model": "myblogapp.Skill",
        "pk": 12,
        "fields": {
            "type": "javascript",
            "title": "以下内容仅做测试使用，文章内容不具有任何意义",
            "abstract": "很多网站登录时都采用了极验验证码作为区分正常用户和爬虫程序的方法之一，\n                    B站正是其中的一个，只要掌握了破解的思路和方法，即使是面对不一样的网站也可以采用相似的方法进行破解。\n                    本文主要从破解思路来向大家分享破解的过程，最后后放上源码供大家参考和指正！\n                    本文主要从破解思路来向大家分享破解的过程，最后后放上源码供大家参考和指正！",
            "href": "/skill/js006.html",
            "time": "2019-07-26 14:50"
        }
    },
    {
        "model": "myblogapp.Skill",
        "pk": 13,
        "fields": {
            "type": "python",
            "title": "以下内容仅做测试使用，文章内容不具有任何意义",
            "abstract": "很多网站登录时都采用了极验验证码作为区分正常用户和爬虫程序的方法之一，\n                    B站正是其中的一个，只要掌握了破解的思路和方法，即使是面对不一样的网站也可以采用相似的方法进行破解。\n                    本文主要从破解思路来向大家分享破解的过程，最后后放上源码供大家参考和指正！\n                    本文主要从破解思路来向大家分享破解的过程，最后后放上源码供大家参考和指正！",
            "href": "/skill/py001.html",
            "time": "2019-07-26 14:50"
        }
    },
    {
        "model": "myblogapp.Skill",
        "pk": 14,
        "fields": {
            "type": "Python",
            "title": "以下内容仅做测试使用，文章内容不具有任何意义",
            "abstract": "很多网站登录时都采用了极验验证码作为区分正常用户和爬虫程序的方法之一，\n                    B站正是其中的一个，只要掌握了破解的思路和方法，即使是面对不一样的网站也可以采用相似的方法进行破解。\n                    本文主要从破解思路来向大家分享破解的过程，最后后放上源码供大家参考和指正！\n                    本文主要从破解思路来向大家分享破解的过程，最后后放上源码供大家参考和指正！",
            "href": "/skill/py002.html",
            "time": "2019-07-26 14:50"
        }
    },
    {
        "model": "myblogapp.Skill",
        "pk": 15,
        "fields": {
            "type": "Python",
            "title": "以下内容仅做测试使用，文章内容不具有任何意义",
            "abstract": "很多网站登录时都采用了极验验证码作为区分正常用户和爬虫程序的方法之一，\n                    B站正是其中的一个，只要掌握了破解的思路和方法，即使是面对不一样的网站也可以采用相似的方法进行破解。\n                    本文主要从破解思路来向大家分享破解的过程，最后后放上源码供大家参考和指正！\n                    本文主要从破解思路来向大家分享破解的过程，最后后放上源码供大家参考和指正！",
            "href": "/skill/py003.html",
            "time": "2019-07-26 14:50"
        }
    },
    {
        "model": "myblogapp.Skill",
        "pk": 16,
        "fields": {
            "type": "Python",
            "title": "以下内容仅做测试使用，文章内容不具有任何意义",
            "abstract": "很多网站登录时都采用了极验验证码作为区分正常用户和爬虫程序的方法之一，\n                    B站正是其中的一个，只要掌握了破解的思路和方法，即使是面对不一样的网站也可以采用相似的方法进行破解。\n                    本文主要从破解思路来向大家分享破解的过程，最后后放上源码供大家参考和指正！\n                    本文主要从破解思路来向大家分享破解的过程，最后后放上源码供大家参考和指正！",
            "href": "/skill/py004.html",
            "time": "2019-07-26 14:50"
        }
    },
    {
        "model": "myblogapp.Skill",
        "pk": 17,
        "fields": {
            "type": "Python",
            "title": "以下内容仅做测试使用，文章内容不具有任何意义",
            "abstract": "很多网站登录时都采用了极验验证码作为区分正常用户和爬虫程序的方法之一，\n                    B站正是其中的一个，只要掌握了破解的思路和方法，即使是面对不一样的网站也可以采用相似的方法进行破解。\n                    本文主要从破解思路来向大家分享破解的过程，最后后放上源码供大家参考和指正！\n                    本文主要从破解思路来向大家分享破解的过程，最后后放上源码供大家参考和指正！",
            "href": "/skill/py005.html",
            "time": "2019-07-26 14:50"
        }
    },
    {
        "model": "myblogapp.Skill",
        "pk": 18,
        "fields": {
            "type": "Python",
            "title": "以下内容仅做测试使用，文章内容不具有任何意义",
            "abstract": "很多网站登录时都采用了极验验证码作为区分正常用户和爬虫程序的方法之一，\n                    B站正是其中的一个，只要掌握了破解的思路和方法，即使是面对不一样的网站也可以采用相似的方法进行破解。\n                    本文主要从破解思路来向大家分享破解的过程，最后后放上源码供大家参考和指正！\n                    本文主要从破解思路来向大家分享破解的过程，最后后放上源码供大家参考和指正！",
            "href": "/skill/py006.html",
            "time": "2019-07-26 14:50"
        }
    },
    {
        "model": "myblogapp.Skill",
        "pk": 19,
        "fields": {
            "type": "Python",
            "title": "以下内容仅做测试使用，文章内容不具有任何意义",
            "abstract": "很多网站登录时都采用了极验验证码作为区分正常用户和爬虫程序的方法之一，\n                    B站正是其中的一个，只要掌握了破解的思路和方法，即使是面对不一样的网站也可以采用相似的方法进行破解。\n                    本文主要从破解思路来向大家分享破解的过程，最后后放上源码供大家参考和指正！\n                    本文主要从破解思路来向大家分享破解的过程，最后后放上源码供大家参考和指正！",
            "href": "/skill/py007.html",
            "time": "2019-07-26 14:50"
        }
    },
    {
        "model": "myblogapp.Skill",
        "pk": 20,
        "fields": {
            "type": "vue",
            "title": "以下内容仅做测试使用，文章内容不具有任何意义",
            "abstract": "很多网站登录时都采用了极验验证码作为区分正常用户和爬虫程序的方法之一，\n                    B站正是其中的一个，只要掌握了破解的思路和方法，即使是面对不一样的网站也可以采用相似的方法进行破解。\n                    本文主要从破解思路来向大家分享破解的过程，最后后放上源码供大家参考和指正！\n                    本文主要从破解思路来向大家分享破解的过程，最后后放上源码供大家参考和指正！",
            "href": "/skill/vue001.html",
            "time": "2019-07-26 14:50"
        }
    },
    {
        "model": "myblogapp.Skill",
        "pk": 21,
        "fields": {
            "type": "css",
            "title": "以下内容仅做测试使用，文章内容不具有任何意义",
            "abstract": "很多网站登录时都采用了极验验证码作为区分正常用户和爬虫程序的方法之一，\n                    B站正是其中的一个，只要掌握了破解的思路和方法，即使是面对不一样的网站也可以采用相似的方法进行破解。\n                    本文主要从破解思路来向大家分享破解的过程，最后后放上源码供大家参考和指正！\n                    本文主要从破解思路来向大家分享破解的过程，最后后放上源码供大家参考和指正！",
            "href": "/skill/vue002.html",
            "time": "2019-07-26 14:50"
        }
    },
    {
        "model": "myblogapp.Life",
        "pk": 1,
        "fields": {
            "type": "css",
            "title": "以下内容仅做测试使用，文章内容不具有任何意义",
            "abstract": "很多网站登录时都采用了极验验证码作为区分正常用户和爬虫程序的方法之一，\n                    B站正是其中的一个，只要掌握了破解的思路和方法，即使是面对不一样的网站也可以采用相似的方法进行破解。\n                    本文主要从破解思路来向大家分享破解的过程，最后后放上源码供大家参考和指正！\n                    本文主要从破解思路来向大家分享破解的过程，最后后放上源码供大家参考和指正！",
            "href": "/skill/vue002.html",
            "time": "2019-07-26 14:50"
        }
    }
]